[
    {
    "tittle": "Aceite oliva 1",
    "text": "Voluptatibus enim rerum expedita itaque aliquam quo. Non quis inventore sunt asperiores vitae.",
    "image": "http://placeimg.com/640/480/nature",
    "categoria": "aceites",
    "price": 3500,
    "id": "1"
    },
    {
    "tittle": "Aceite oliva 2",
    "text": "Voluptatibus enim rerum expedita itaque aliquam quo. Non quis inventore sunt asperiores vitae.",
    "image": "http://placeimg.com/640/480/nature",
    "categoria": "aceites",
    "price": 15,
    "id": "2"
    },
    {
    "tittle": "Aceite oliva 3",
    "text": "Voluptatibus enim rerum expedita itaque aliquam quo. Non quis inventore sunt asperiores vitae.",
    "image": "http://placeimg.com/640/480/nature",
    "categoria": "aceites",
    "price": 15,
    "id": "3"
    },
    {
    "tittle": "Aceite oliva 4",
    "text": "Voluptatibus enim rerum expedita itaque aliquam quo. Non quis inventore sunt asperiores vitae.",
    "image": "http://placeimg.com/640/480/nature",
    "categoria": "aceites",
    "price": 15,
    "id": "4"
    },
    {
    "tittle": "Aceite oliva 5",
    "text": "Voluptatibus enim rerum expedita itaque aliquam quo. Non quis inventore sunt asperiores vitae.",
    "image": "http://placeimg.com/640/480/nature",
    "categoria": "aceites",
    "price": 15,
    "id": "5"
    },
    {
    "tittle": "Cuarzo 1",
    "text": "Praesentium recusandae qui perspiciatis qui. Incidunt quia magnam ipsum blanditiis.",
    "image": "http://placeimg.com/640/480/nature",
    "categoria": "cuarzos",
    "price": 15,
    "id": "6"
    },
    {
    "tittle": "Cuarzo 2",
    "text": "Voluptatibus enim rerum expedita itaque aliquam quo. Non quis inventore sunt asperiores vitae.",
    "image": "http://placeimg.com/640/480/nature",
    "categoria": "cuarzos",
    "price": 15,
    "id": "7"
    },
    {
    "tittle": "Cuarzo 3",
    "text": "Voluptatibus enim rerum expedita itaque aliquam quo. Non quis inventore sunt asperiores vitae.",
    "image": "http://placeimg.com/640/480/nature",
    "categoria": "cuarzos",
    "price": 15,
    "id": "8"
    },
    {
    "tittle": "Cuarzo 4",
    "text": "Voluptatibus enim rerum expedita itaque aliquam quo. Non quis inventore sunt asperiores vitae.",
    "image": "http://placeimg.com/640/480/nature",
    "categoria": "cuarzos",
    "price": 15,
    "id": "9"
    },
    {
    "tittle": "Cuarzo 5",
    "text": "Voluptatibus enim rerum expedita itaque aliquam quo. Non quis inventore sunt asperiores vitae.",
    "image": "http://placeimg.com/640/480/nature",
    "categoria": "cuarzos",
    "price": 15,
    "id": "10"
    },
    {
    "tittle": "Amuleto 1",
    "text": "Voluptatibus enim rerum expedita itaque aliquam quo. Non quis inventore sunt asperiores vitae.",
    "image": "http://placeimg.com/640/480/nature",
    "categoria": "amuletos",
    "price": 15,
    "id": "11"
    },
    {
    "tittle": "Amuleto 2",
    "text": "Voluptatibus enim rerum expedita itaque aliquam quo. Non quis inventore sunt asperiores vitae.",
    "image": "http://placeimg.com/640/480/nature",
    "categoria": "amuletos",
    "price": 15,
    "id": "12"
    },
    {
    "tittle": "Amuleto 3",
    "text": "Voluptatibus enim rerum expedita itaque aliquam quo. Non quis inventore sunt asperiores vitae.",
    "image": "http://placeimg.com/640/480/nature",
    "categoria": "amuletos",
    "price": 15,
    "id": "13"
    },
    {
    "tittle": "Amuleto 4",
    "text": "Voluptatibus enim rerum expedita itaque aliquam quo. Non quis inventore sunt asperiores vitae.",
    "image": "http://placeimg.com/640/480/nature",
    "categoria": "amuletos",
    "price": 15,
    "id": "14"
    },
    {
    "tittle": "Amuleto 5",
    "text": "Voluptatibus enim rerum expedita itaque aliquam quo. Non quis inventore sunt asperiores vitae.",
    "image": "http://placeimg.com/640/480/nature",
    "categoria": "amuletos",
    "price": 15,
    "id": "15"
    },
    {
    "tittle": "Incienso 1",
    "text": "Voluptatibus enim rerum expedita itaque aliquam quo. Non quis inventore sunt asperiores vitae.",
    "image": "http://placeimg.com/640/480/nature",
    "categoria": "inciensos",
    "price": 15,
    "id": "16"
    },
    {
    "tittle": "Incienso 2",
    "text": "Voluptatibus enim rerum expedita itaque aliquam quo. Non quis inventore sunt asperiores vitae.",
    "image": "http://placeimg.com/640/480/nature",
    "categoria": "inciensos",
    "price": 15,
    "id": "17"
    },
    {
    "tittle": "Incienso 3",
    "text": "Voluptatibus enim rerum expedita itaque aliquam quo. Non quis inventore sunt asperiores vitae.",
    "image": "http://placeimg.com/640/480/nature",
    "categoria": "inciensos",
    "price": 15,
    "id": "18"
    },
    {
    "tittle": "Incienso 4",
    "text": "Voluptatibus enim rerum expedita itaque aliquam quo. Non quis inventore sunt asperiores vitae.",
    "image": "http://placeimg.com/640/480/arch",
    "categoria": "inciensos",
    "price": 15,
    "id": "19"
    },
    {
    "tittle": "Incienso 5",
    "text": "Voluptatibus enim rerum expedita itaque aliquam quo. Non quis inventore sunt asperiores vitae.",
    "image": "http://placeimg.com/640/480/arch",
    "categoria": "inciensos",
    "price": 15,
    "id": "20"
    }
    ]